dartsflash/__init__.py
dartsflash/components.py
dartsflash/dartsflash.py
dartsflash/diagram.py
dartsflash/hyflash.py
dartsflash/libflash.cpython-38-x86_64-linux-gnu.so
dartsflash/mixtures.py
dartsflash/plot.py
open_darts_flash-0.10.2.dist-info/LICENSE
open_darts_flash-0.10.2.dist-info/METADATA
open_darts_flash-0.10.2.dist-info/WHEEL
open_darts_flash-0.10.2.dist-info/top_level.txt
open_darts_flash-0.10.2.dist-info/RECORD
