Metadata-Version: 2.1
Name: open-darts-flash
Version: 0.10.2
Summary: Multiphase equilibrium and thermodynamic models for subsurface energy transition applications
Author-email: Michiel Wapperom <M.B.Wapperom@tudelft.nl>
License: 
Project-URL: Homepage, https://gitlab.com/open-darts/open-darts-flash
Keywords: flash,multiphase,simulation
Classifier: License :: OSI Approved :: Apache Software License
Classifier: Programming Language :: Python :: 3
Classifier: Programming Language :: Python :: 3.8
Classifier: Programming Language :: Python :: 3.9
Classifier: Programming Language :: Python :: 3.10
Classifier: Programming Language :: Python :: 3.11
Classifier: Programming Language :: Python :: 3.12
Classifier: Programming Language :: Python :: 3 :: Only
Requires-Python: >=3.8
License-File: LICENSE
Requires-Dist: numpy
Requires-Dist: xarray
Provides-Extra: docs
Requires-Dist: myst-parser; extra == "docs"
Requires-Dist: sphinx-rtd-theme; extra == "docs"
Requires-Dist: sphinx; extra == "docs"
Requires-Dist: sphinx-tabs; extra == "docs"
Requires-Dist: sphinx-inline-tabs; extra == "docs"
Requires-Dist: sphinxcontrib-matlabdomain; extra == "docs"
Requires-Dist: sphinxcontrib-bibtex; extra == "docs"
Requires-Dist: linkify-it-py; extra == "docs"
Requires-Dist: sphinx-copybutton; extra == "docs"
Provides-Extra: plot
Requires-Dist: matplotlib; extra == "plot"
Provides-Extra: test
Requires-Dist: pytest; extra == "test"
Requires-Dist: h5netCDF; extra == "test"
